tclf/__init__.py
tclf/classical_classifier.py
tclf/types.py
tclf-0.0.9.dist-info/LICENSE
tclf-0.0.9.dist-info/METADATA
tclf-0.0.9.dist-info/WHEEL
tclf-0.0.9.dist-info/top_level.txt
tclf-0.0.9.dist-info/RECORD
