Metadata-Version: 2.1
Name: tclf
Version: 0.0.9
Summary: Classify trades using trade classification algorithms 🐍
Author-email: Markus Bilz <github@markusbilz.com>
Project-URL: Homepage, https://github.com/KarelZe/tclf
Project-URL: Bug Tracker, https://github.com/KarelZe/tclf/issues
Classifier: Development Status :: 3 - Alpha
Classifier: Programming Language :: Python :: 3 :: Only
Classifier: Programming Language :: Python :: 3.8
Classifier: Programming Language :: Python :: 3.9
Classifier: Programming Language :: Python :: 3.10
Classifier: Programming Language :: Python :: 3.11
Classifier: Programming Language :: Python :: 3.12
Classifier: Operating System :: OS Independent
Classifier: Intended Audience :: Information Technology
Classifier: Intended Audience :: Science/Research
Classifier: Topic :: Scientific/Engineering
Classifier: Topic :: Scientific/Engineering :: Artificial Intelligence
Requires-Python: >=3.8
License-File: LICENSE
Requires-Dist: numpy
Requires-Dist: pandas
Requires-Dist: scikit-learn
